dumbmake/__init__.py
dumbmake/dumbmake.py
dumbmake/test/__init__.py
dumbmake/test/test_dumbmake.py
mozbuild/__init__.py
mozbuild/android_version_code.py
mozbuild/artifacts.py
mozbuild/base.py
mozbuild/chunkify.py
mozbuild/config_status.py
mozbuild/doctor.py
mozbuild/dotproperties.py
mozbuild/html_build_viewer.py
mozbuild/jar.py
mozbuild/mach_commands.py
mozbuild/makeutil.py
mozbuild/milestone.py
mozbuild/mozconfig.py
mozbuild/mozinfo.py
mozbuild/preprocessor.py
mozbuild/pythonutil.py
mozbuild/repackage.py
mozbuild/shellutil.py
mozbuild/sphinx.py
mozbuild/testing.py
mozbuild/util.py
mozbuild/vendor_rust.py
mozbuild/virtualenv.py
mozbuild/action/7z_exe_archive.py
mozbuild/action/7z_exe_extract.py
mozbuild/action/__init__.py
mozbuild/action/buildlist.py
mozbuild/action/cl.py
mozbuild/action/dump_env.py
mozbuild/action/dumpsymbols.py
mozbuild/action/explode_aar.py
mozbuild/action/file_generate.py
mozbuild/action/generate_browsersearch.py
mozbuild/action/generate_searchjson.py
mozbuild/action/generate_suggestedsites.py
mozbuild/action/generate_symbols_file.py
mozbuild/action/jar_maker.py
mozbuild/action/make_dmg.py
mozbuild/action/make_unzip.py
mozbuild/action/make_zip.py
mozbuild/action/output_searchplugins_list.py
mozbuild/action/package_fennec_apk.py
mozbuild/action/preprocessor.py
mozbuild/action/process_define_files.py
mozbuild/action/process_install_manifest.py
mozbuild/action/test_archive.py
mozbuild/action/unpack_dmg.py
mozbuild/action/webidl.py
mozbuild/action/xpccheck.py
mozbuild/action/xpidl-process.py
mozbuild/action/zip.py
mozbuild/backend/__init__.py
mozbuild/backend/android_eclipse.py
mozbuild/backend/base.py
mozbuild/backend/common.py
mozbuild/backend/configenvironment.py
mozbuild/backend/cpp_eclipse.py
mozbuild/backend/fastermake.py
mozbuild/backend/mach_commands.py
mozbuild/backend/recursivemake.py
mozbuild/backend/test_manifest.py
mozbuild/backend/tup.py
mozbuild-0.3.dist-info/DESCRIPTION.rst
mozbuild-0.3.dist-info/METADATA
mozbuild-0.3.dist-info/RECORD
mozbuild-0.3.dist-info/WHEEL
mozbuild-0.3.dist-info/metadata.json
mozbuild-0.3.dist-info/top_level.txt
