Metadata-Version: 2.0
Name: mozbuild
Version: 0.3
Summary: Mozilla build system functionality.
Home-page: UNKNOWN
Author: Mozilla Foundation
Author-email: dev-builds@lists.mozilla.org
License: MPL 2.0
Keywords: mozilla build
Platform: UNKNOWN
Classifier: Development Status :: 3 - Alpha
Classifier: Topic :: Software Development :: Build Tools
Classifier: License :: OSI Approved :: Mozilla Public License 2.0 (MPL 2.0)
Classifier: Programming Language :: Python :: 2.7
Classifier: Programming Language :: Python :: Implementation :: CPython
Requires-Dist: jsmin
Requires-Dist: mozfile
